thirdai/deployment.py
thirdai/distributed_bolt.py
thirdai/embeddings.py
thirdai/hashing.py
thirdai/licensing.py
thirdai/search.py
thirdai/_download.py
thirdai/_thirdai.cp38-win_amd64.pyd
thirdai/__init__.py
thirdai/bolt/ner_modifications.py
thirdai/bolt/udt_docs.py
thirdai/bolt/udt_modifications.py
thirdai/bolt/__init__.py
thirdai/bolt/udt_builder/model_templates.py
thirdai/bolt/udt_builder/task_detector.py
thirdai/bolt/udt_builder/__init__.py
thirdai/bolt/udt_builder/column_inferencing/columns.py
thirdai/bolt/udt_builder/column_inferencing/column_detector.py
thirdai/bolt/udt_builder/column_inferencing/utils.py
thirdai/bolt/udt_builder/column_inferencing/__init__.py
thirdai/data/column_map_utils.py
thirdai/data/get_udt_columns.py
thirdai/data/type_inference.py
thirdai/data/__init__.py
thirdai/dataset/bolt_ner_data_source.py
thirdai/dataset/csv_data_source.py
thirdai/dataset/data_source.py
thirdai/dataset/llm_data_source.py
thirdai/dataset/parquet_data_source.py
thirdai/dataset/ray_data_source.py
thirdai/dataset/__init__.py
thirdai/demos/beir_download_utils.py
thirdai/demos/download_datasets.py
thirdai/demos/download_tokenizer_vocabs.py
thirdai/demos/__init__.py
thirdai/gen/questions.py
thirdai/gen/__init__.py
thirdai/neural_db/connectors.py
thirdai/neural_db/constraint_matcher.py
thirdai/neural_db/documents.py
thirdai/neural_db/inverted_index.py
thirdai/neural_db/loggers.py
thirdai/neural_db/neural_db.py
thirdai/neural_db/question_generation.py
thirdai/neural_db/savable_state.py
thirdai/neural_db/sharded_documents.py
thirdai/neural_db/sql_helpers.py
thirdai/neural_db/supervised_datasource.py
thirdai/neural_db/table.py
thirdai/neural_db/teachers.py
thirdai/neural_db/utils.py
thirdai/neural_db/__init__.py
thirdai/neural_db/models/finetunable_retriever.py
thirdai/neural_db/models/mach.py
thirdai/neural_db/models/mach_defaults.py
thirdai/neural_db/models/mach_mixture_model.py
thirdai/neural_db/models/models.py
thirdai/neural_db/models/model_interface.py
thirdai-0.9.33.dist-info/DELVEWHEEL
thirdai-0.9.33.dist-info/LICENSE.txt
thirdai-0.9.33.dist-info/METADATA
thirdai-0.9.33.dist-info/RECORD
thirdai-0.9.33.dist-info/top_level.txt
thirdai-0.9.33.dist-info/WHEEL
