Metadata-Version: 2.1
Name: thirdai
Version: 0.9.33
Summary: A faster cpu machine learning library
Author: ThirdAI
Author-email: contact@thirdai.com
License: proprietary
License-File: LICENSE.txt
Requires-Dist: numpy
Requires-Dist: typing-extensions
Requires-Dist: requests
Requires-Dist: pandas (>=2.0.0)
Requires-Dist: PyTrie
Requires-Dist: PyMuPDF
Requires-Dist: langchain
Requires-Dist: langchain-community
Requires-Dist: bs4
Requires-Dist: trafilatura
Requires-Dist: python-docx
Requires-Dist: url-normalize
Requires-Dist: nltk (>=3.8.2)
Requires-Dist: dask[complete]
Requires-Dist: unidecode
Requires-Dist: pydantic
Requires-Dist: sortedcontainers
Requires-Dist: SQLAlchemy (>=2.0.0)
Requires-Dist: scikit-learn
Requires-Dist: Office365-REST-Python-Client
Requires-Dist: simple-salesforce
Requires-Dist: ipython
Requires-Dist: pdfplumber (!=0.11.3)
Requires-Dist: lxml-html-clean
Requires-Dist: openai (>=1.0.0)
Requires-Dist: tqdm
Provides-Extra: benchmark
Requires-Dist: toml ; extra == 'benchmark'
Requires-Dist: psutil ; extra == 'benchmark'
Requires-Dist: scikit-learn ; extra == 'benchmark'
Requires-Dist: mlflow ; extra == 'benchmark'
Requires-Dist: protobuf ; extra == 'benchmark'
Requires-Dist: boto3 ; extra == 'benchmark'
Requires-Dist: s3fs ; extra == 'benchmark'
Requires-Dist: gcsfs ; extra == 'benchmark'
Requires-Dist: nltk (>=3.8.2) ; extra == 'benchmark'
Requires-Dist: ray[default] ; extra == 'benchmark'
Requires-Dist: torch ; extra == 'benchmark'
Requires-Dist: unstructured[all-docs] (<=0.10.20) ; extra == 'benchmark'
Requires-Dist: PyTrie ; extra == 'benchmark'
Requires-Dist: PyMuPDF ; extra == 'benchmark'
Requires-Dist: langchain ; extra == 'benchmark'
Requires-Dist: langchain-community ; extra == 'benchmark'
Requires-Dist: bs4 ; extra == 'benchmark'
Requires-Dist: trafilatura ; extra == 'benchmark'
Requires-Dist: python-docx ; extra == 'benchmark'
Requires-Dist: url-normalize ; extra == 'benchmark'
Requires-Dist: dask[complete] ; extra == 'benchmark'
Requires-Dist: unidecode ; extra == 'benchmark'
Requires-Dist: pydantic ; extra == 'benchmark'
Requires-Dist: sortedcontainers ; extra == 'benchmark'
Requires-Dist: SQLAlchemy (>=2.0.0) ; extra == 'benchmark'
Requires-Dist: Office365-REST-Python-Client ; extra == 'benchmark'
Requires-Dist: simple-salesforce ; extra == 'benchmark'
Requires-Dist: ipython ; extra == 'benchmark'
Requires-Dist: pdfplumber (!=0.11.3) ; extra == 'benchmark'
Requires-Dist: lxml-html-clean ; extra == 'benchmark'
Requires-Dist: openai (>=1.0.0) ; extra == 'benchmark'
Requires-Dist: tqdm ; extra == 'benchmark'
Provides-Extra: docs
Requires-Dist: sphinx (!=5.2.0.post0) ; extra == 'docs'
Requires-Dist: sphinx-rtd-theme ; extra == 'docs'
Requires-Dist: PyTrie ; extra == 'docs'
Requires-Dist: PyMuPDF ; extra == 'docs'
Requires-Dist: langchain ; extra == 'docs'
Requires-Dist: langchain-community ; extra == 'docs'
Requires-Dist: bs4 ; extra == 'docs'
Requires-Dist: trafilatura ; extra == 'docs'
Requires-Dist: python-docx ; extra == 'docs'
Requires-Dist: url-normalize ; extra == 'docs'
Requires-Dist: nltk (>=3.8.2) ; extra == 'docs'
Requires-Dist: dask[complete] ; extra == 'docs'
Requires-Dist: unidecode ; extra == 'docs'
Requires-Dist: pydantic ; extra == 'docs'
Requires-Dist: sortedcontainers ; extra == 'docs'
Requires-Dist: SQLAlchemy (>=2.0.0) ; extra == 'docs'
Requires-Dist: scikit-learn ; extra == 'docs'
Requires-Dist: Office365-REST-Python-Client ; extra == 'docs'
Requires-Dist: simple-salesforce ; extra == 'docs'
Requires-Dist: ipython ; extra == 'docs'
Requires-Dist: pdfplumber (!=0.11.3) ; extra == 'docs'
Requires-Dist: lxml-html-clean ; extra == 'docs'
Requires-Dist: openai (>=1.0.0) ; extra == 'docs'
Requires-Dist: tqdm ; extra == 'docs'
Provides-Extra: neural_db
Requires-Dist: PyTrie ; extra == 'neural_db'
Requires-Dist: PyMuPDF ; extra == 'neural_db'
Requires-Dist: langchain ; extra == 'neural_db'
Requires-Dist: langchain-community ; extra == 'neural_db'
Requires-Dist: bs4 ; extra == 'neural_db'
Requires-Dist: trafilatura ; extra == 'neural_db'
Requires-Dist: python-docx ; extra == 'neural_db'
Requires-Dist: url-normalize ; extra == 'neural_db'
Requires-Dist: nltk (>=3.8.2) ; extra == 'neural_db'
Requires-Dist: dask[complete] ; extra == 'neural_db'
Requires-Dist: unidecode ; extra == 'neural_db'
Requires-Dist: pydantic ; extra == 'neural_db'
Requires-Dist: sortedcontainers ; extra == 'neural_db'
Requires-Dist: SQLAlchemy (>=2.0.0) ; extra == 'neural_db'
Requires-Dist: scikit-learn ; extra == 'neural_db'
Requires-Dist: Office365-REST-Python-Client ; extra == 'neural_db'
Requires-Dist: simple-salesforce ; extra == 'neural_db'
Requires-Dist: ipython ; extra == 'neural_db'
Requires-Dist: pdfplumber (!=0.11.3) ; extra == 'neural_db'
Requires-Dist: lxml-html-clean ; extra == 'neural_db'
Requires-Dist: openai (>=1.0.0) ; extra == 'neural_db'
Requires-Dist: tqdm ; extra == 'neural_db'
Provides-Extra: neural_db_v2
Requires-Dist: pandas ; extra == 'neural_db_v2'
Requires-Dist: pandera ; extra == 'neural_db_v2'
Requires-Dist: sqlalchemy-utils ; extra == 'neural_db_v2'
Requires-Dist: transformers ; extra == 'neural_db_v2'
Requires-Dist: torch ; extra == 'neural_db_v2'
Requires-Dist: unstructured[pptx] (<=0.10.20) ; extra == 'neural_db_v2'
Provides-Extra: test
Requires-Dist: pytest ; extra == 'test'
Requires-Dist: pytest-mock ; extra == 'test'
Requires-Dist: boto3 ; extra == 'test'
Requires-Dist: moto[s3,server] ; extra == 'test'
Requires-Dist: mlflow ; extra == 'test'
Requires-Dist: protobuf ; extra == 'test'
Requires-Dist: datasets ; extra == 'test'
Requires-Dist: torch ; extra == 'test'
Requires-Dist: toml ; extra == 'test'
Requires-Dist: psutil ; extra == 'test'
Requires-Dist: transformers ; extra == 'test'
Requires-Dist: cryptography ; extra == 'test'
Requires-Dist: tokenizers (<=0.20.3) ; extra == 'test'
Requires-Dist: pyarrow ; extra == 'test'
Requires-Dist: prometheus-client ; extra == 'test'
Requires-Dist: gcsfs ; extra == 'test'
Requires-Dist: s3fs ; extra == 'test'
Requires-Dist: mock ; extra == 'test'
Requires-Dist: scikit-learn ; extra == 'test'
Requires-Dist: pyOpenSSL (>22.1.0) ; extra == 'test'
Requires-Dist: ray ; extra == 'test'
Requires-Dist: grpcio ; extra == 'test'
Requires-Dist: unstructured[all-docs] (<=0.10.20) ; extra == 'test'
Requires-Dist: faker ; extra == 'test'
Requires-Dist: PyTrie ; extra == 'test'
Requires-Dist: PyMuPDF ; extra == 'test'
Requires-Dist: langchain ; extra == 'test'
Requires-Dist: langchain-community ; extra == 'test'
Requires-Dist: bs4 ; extra == 'test'
Requires-Dist: trafilatura ; extra == 'test'
Requires-Dist: python-docx ; extra == 'test'
Requires-Dist: url-normalize ; extra == 'test'
Requires-Dist: nltk (>=3.8.2) ; extra == 'test'
Requires-Dist: dask[complete] ; extra == 'test'
Requires-Dist: unidecode ; extra == 'test'
Requires-Dist: pydantic ; extra == 'test'
Requires-Dist: sortedcontainers ; extra == 'test'
Requires-Dist: SQLAlchemy (>=2.0.0) ; extra == 'test'
Requires-Dist: Office365-REST-Python-Client ; extra == 'test'
Requires-Dist: simple-salesforce ; extra == 'test'
Requires-Dist: ipython ; extra == 'test'
Requires-Dist: pdfplumber (!=0.11.3) ; extra == 'test'
Requires-Dist: lxml-html-clean ; extra == 'test'
Requires-Dist: openai (>=1.0.0) ; extra == 'test'
Requires-Dist: tqdm ; extra == 'test'
Requires-Dist: pandas ; extra == 'test'
Requires-Dist: pandera ; extra == 'test'
Requires-Dist: sqlalchemy-utils ; extra == 'test'
Requires-Dist: unstructured[pptx] (<=0.10.20) ; extra == 'test'
